codemod_dockerfile/__init__.py
codemod_dockerfile-0.0.0a1.dist-info/METADATA
codemod_dockerfile-0.0.0a1.dist-info/WHEEL
codemod_dockerfile-0.0.0a1.dist-info/RECORD
